[
    {
        "nombre": "John Doe",
        "nacionalidad": "Estados Unidos",
        "numero_de_id": "X10000123",
        "vuelo": "V715",
        "horas_de_vuelo": 300,
        "tipo_de_licencia": "PPL"
    },
    {
        "nombre": "Jane Smith",
        "nacionalidad": "Reino Unido",
        "numero_de_id": "X20000123",
        "vuelo": "V714",
        "horas_de_vuelo": 100,
        "tipo_de_licencia": "CPL"
    },
    {
        "nombre": "Marta Rodríguez",
        "nacionalidad": "España",
        "numero_de_id": "X30000123",
        "vuelo": "V713",
        "horas_de_vuelo": 150,
        "tipo_de_licencia": "CPL"
    },
    {
        "nombre": "Carlos García",
        "nacionalidad": "Colombia",
        "numero_de_id": "X40000123",
        "vuelo": "V712",
        "horas_de_vuelo": 640,
        "tipo_de_licencia": "PPL"
    },
    {
        "nombre": "Aisha Ahmed",
        "nacionalidad": "Egipto",
        "numero_de_id": "X50000123",
        "vuelo": "V711",
        "horas_de_vuelo": 175,
        "tipo_de_licencia": "CPL"
    },
    {
        "nombre": "Miguel Pereira",
        "nacionalidad": "Brasil",
        "numero_de_id": "X60000123",
        "vuelo": "V710",
        "horas_de_vuelo": 80,
        "tipo_de_licencia": "CPL"
    },
    {
        "nombre": "Isabella Santos",
        "nacionalidad": "Portugal",
        "numero_de_id": "X70000123",
        "vuelo": "V709",
        "horas_de_vuelo": 215,
        "tipo_de_licencia": "PPL"
    },
    {
        "nombre": "Olga Ivanova",
        "nacionalidad": "Rusia",
        "numero_de_id": "X80000123",
        "vuelo": "V708",
        "horas_de_vuelo": 295,
        "tipo_de_licencia": "CPL"
    },
    {
        "nombre": "Jürgen Schmidt",
        "nacionalidad": "Alemania",
        "numero_de_id": "X90000123",
        "vuelo": "V707",
        "horas_de_vuelo": 70,
        "tipo_de_licencia": "CPL"
    },
    {
        "nombre": "Chen Wei",
        "nacionalidad": "China",
        "numero_de_id": "X01000123",
        "vuelo": "V706",
        "horas_de_vuelo": 235,
        "tipo_de_licencia": "PPL"
    },
    {
        "nombre": "Hans Müller",
        "nacionalidad": "Alemania",
        "numero_de_id": "X02000123",
        "vuelo": "V705",
        "horas_de_vuelo": 305,
        "tipo_de_licencia": "CPL"
    },
    {
        "nombre": "Priya Sharma",
        "nacionalidad": "India",
        "numero_de_id": "X03000123",
        "vuelo": "V704",
        "horas_de_vuelo": 190,
        "tipo_de_licencia": "CPL"
    },
    {
        "nombre": "Luca Rossi",
        "nacionalidad": "Italia",
        "numero_de_id": "X04000123",
        "vuelo": "V703",
        "horas_de_vuelo": 120,
        "tipo_de_licencia": "PPL"
    },
    {
        "nombre": "Emily Brown",
        "nacionalidad": "Canada",
        "numero_de_id": "X05000123",
        "vuelo": "V702",
        "horas_de_vuelo": 40,
        "tipo_de_licencia": "CPL"
    },
    {
        "nombre": "Fatima Al-Sayed",
        "nacionalidad": "Arabia Saudita",
        "numero_de_id": "X06000123",
        "vuelo": "V701",
        "horas_de_vuelo": 365,
        "tipo_de_licencia": "CPL"
    },
    {
        "nombre": "Thabo Ndlovu",
        "nacionalidad": "Nigeria",
        "numero_de_id": "X07000123",
        "vuelo": "V700",
        "horas_de_vuelo": 999,
        "tipo_de_licencia": "PPL"
    }
]
   